completion/__init__.py
completion/git-machete.completion.bash
completion/git-machete.completion.zsh
completion/git-machete.fish
docs/man/git-machete.1
git_machete/__init__.py
git_machete/annotation.py
git_machete/bin.py
git_machete/cli.py
git_machete/code_hosting.py
git_machete/constants.py
git_machete/exceptions.py
git_machete/generated_docs.py
git_machete/git_config_keys.py
git_machete/git_operations.py
git_machete/github.py
git_machete/gitlab.py
git_machete/options.py
git_machete/utils.py
git_machete/client/__init__.py
git_machete/client/advance.py
git_machete/client/anno.py
git_machete/client/base.py
git_machete/client/diff.py
git_machete/client/discover.py
git_machete/client/fork_point.py
git_machete/client/go_interactive.py
git_machete/client/go_show.py
git_machete/client/log.py
git_machete/client/slide_out.py
git_machete/client/squash.py
git_machete/client/traverse.py
git_machete/client/update.py
git_machete/client/with_code_hosting.py
git_machete-3.39.0.dist-info/licenses/LICENSE
git_machete-3.39.0.dist-info/METADATA
git_machete-3.39.0.dist-info/WHEEL
git_machete-3.39.0.dist-info/entry_points.txt
git_machete-3.39.0.dist-info/top_level.txt
git_machete-3.39.0.dist-info/RECORD
