Metadata-Version: 2.4
Name: git-machete
Version: 3.39.0
Summary: Probably the sharpest git repository organizer & rebase/merge workflow automation tool you've ever seen
Home-page: https://github.com/VirtusLab/git-machete
Author: VirtusLab
Author-email: gitmachete@virtuslab.com
License: MIT
Keywords: git
Classifier: Programming Language :: Python
Classifier: Programming Language :: Python :: 3
Classifier: Development Status :: 5 - Production/Stable
Classifier: Environment :: Console
Classifier: Intended Audience :: Developers
Classifier: Intended Audience :: Information Technology
Classifier: Operating System :: OS Independent
Requires-Python: >=3.6, <4
License-File: LICENSE
Dynamic: author
Dynamic: author-email
Dynamic: classifier
Dynamic: description
Dynamic: description-content-type
Dynamic: home-page
Dynamic: keywords
Dynamic: license
Dynamic: license-file
Dynamic: requires-python
Dynamic: summary
